lucid/__init__.py
lucid/aws.py
lucid/db.py
lucid/df.py
lucid/gcp.py
lucid/io.py
lucid/util.py
lucid/viz.py
lucid/j2/dt_basic.j2.html
lucid_data-0.1.4.dist-info/LICENSE
lucid_data-0.1.4.dist-info/METADATA
lucid_data-0.1.4.dist-info/WHEEL
lucid_data-0.1.4.dist-info/top_level.txt
lucid_data-0.1.4.dist-info/RECORD
