Metadata-Version: 2.1
Name: lucid-data
Version: 0.1.4
Summary: Scripts for processing, profiling, and publishing data
Home-page: https://github.com/liquidcarbon/lucid
Author: Alex Kislukhin
Author-email: liquidc@gmail.com
License: MIT
Platform: UNKNOWN
Classifier: License :: OSI Approved :: MIT License
Classifier: Operating System :: OS Independent
Classifier: Programming Language :: Python :: 3
Requires-Python: >=3.7
Requires-Dist: bokeh
Requires-Dist: boto3
Requires-Dist: matplotlib
Requires-Dist: pandas
Requires-Dist: requests
Requires-Dist: scipy
